dev_utils/__init__.py
dev_utils/abstract.py
dev_utils/common/__init__.py
dev_utils/common/datetime.py
dev_utils/common/envs.py
dev_utils/common/humanize.py
dev_utils/common/inspect.py
dev_utils/common/strings.py
dev_utils/guards.py
dev_utils/py.typed
dev_utils/results.py
python_dev_utils-7.0.1.dist-info/METADATA
python_dev_utils-7.0.1.dist-info/WHEEL
python_dev_utils-7.0.1.dist-info/licenses/LICENCE
python_dev_utils-7.0.1.dist-info/RECORD
