Metadata-Version: 2.1
Name: python_dev_utils
Version: 7.0.1
Summary: My project utils package, that I use in my projects.
Author-Email: Dmitriy Lunev <dima.lunev14@gmail.com>
License: MIT
Requires-Python: >=3.11
